{"result":[{"addr_name":"강서구","cd":"21120","full_addr":"부산광역시 강서구","y_coor":"1683579","x_coor":"1126269"},{"addr_name":"금정구","cd":"21110","full_addr":"부산광역시 금정구","y_coor":"1697100","x_coor":"1144771"},{"addr_name":"기장군","cd":"21510","full_addr":"부산광역시 기장군","y_coor":"1701586","x_coor":"1154663"},{"addr_name":"남구","cd":"21070","full_addr":"부산광역시 남구","y_coor":"1682717","x_coor":"1145045"},{"addr_name":"동구","cd":"21030","full_addr":"부산광역시 동구","y_coor":"1682549","x_coor":"1140751"},{"addr_name":"동래구","cd":"21060","full_addr":"부산광역시 동래구","y_coor":"1691233","x_coor":"1143740"},{"addr_name":"부산진구","cd":"21050","full_addr":"부산광역시 부산진구","y_coor":"1686647","x_coor":"1140531"},{"addr_name":"북구","cd":"21080","full_addr":"부산광역시 북구","y_coor":"1693720","x_coor":"1138630"},{"addr_name":"사상구","cd":"21150","full_addr":"부산광역시 사상구","y_coor":"1685766","x_coor":"1135397"},{"addr_name":"사하구","cd":"21100","full_addr":"부산광역시 사하구","y_coor":"1678777","x_coor":"1134459"},{"addr_name":"서구","cd":"21020","full_addr":"부산광역시 서구","y_coor":"1676689","x_coor":"1138120"},{"addr_name":"수영구","cd":"21140","full_addr":"부산광역시 수영구","y_coor":"1686292","x_coor":"1146757"},{"addr_name":"연제구","cd":"21130","full_addr":"부산광역시 연제구","y_coor":"1688599","x_coor":"1144137"},{"addr_name":"영도구","cd":"21040","full_addr":"부산광역시 영도구","y_coor":"1677166","x_coor":"1142434"},{"addr_name":"중구","cd":"21010","full_addr":"부산광역시 중구","y_coor":"1679989","x_coor":"1139637"},{"addr_name":"해운대구","cd":"21090","full_addr":"부산광역시 해운대구","y_coor":"1689959","x_coor":"1150545"}],"errCd":0,"errMsg":"Success","id":"API_0701","trId":"R5rx_API_0701_1767627935036"}
